xtestlib/__init__.py
xtestlib-0.0.1.dist-info/METADATA
xtestlib-0.0.1.dist-info/WHEEL
xtestlib-0.0.1.dist-info/top_level.txt
xtestlib-0.0.1.dist-info/RECORD
