Metadata-Version: 2.1
Name: xtestlib
Version: 0.0.1
Summary: Lib to test deployments and features
